gpscraper/__init__.py
gpscraper/exceptions.py
gpscraper/headers.py
gpscraper/utils.py
gpscraper/forms/__init__.py
gpscraper/forms/permissions.py
gpscraper/forms/review_history.py
gpscraper/forms/reviews.py
gpscraper/forms/search.py
gpscraper/parsers/__init__.py
gpscraper/parsers/details.py
gpscraper/parsers/permissions.py
gpscraper/parsers/review_history.py
gpscraper/parsers/reviews.py
gpscraper/parsers/search.py
gpscraper/scrapers/__init__.py
gpscraper/scrapers/details.py
gpscraper/scrapers/ebook_search.py
gpscraper/scrapers/general.py
gpscraper/scrapers/permissions.py
gpscraper/scrapers/review_history.py
gpscraper/scrapers/reviews.py
gpscraper/scrapers/search.py
gpscraper/validators/__init__.py
gpscraper/validators/details.py
gpscraper/validators/permissions.py
gpscraper/validators/review_history.py
gpscraper/validators/reviews.py
gpscraper/validators/search.py
gpscraper-1.1.3.dist-info/LICENSE
gpscraper-1.1.3.dist-info/METADATA
gpscraper-1.1.3.dist-info/WHEEL
gpscraper-1.1.3.dist-info/top_level.txt
gpscraper-1.1.3.dist-info/RECORD
