Metadata-Version: 2.1
Name: gpscraper
Version: 1.1.3
Summary: A nice Google Play scraper.
Home-page: https://github.com/alverelt/gpscraper
Author: Alver Lopez
Author-email: alverelt@gmail.com
License: MIT
Platform: UNKNOWN
Classifier: Intended Audience :: Developers
Classifier: License :: OSI Approved :: MIT License
Classifier: Programming Language :: Python :: 3
Requires-Dist: beautifulsoup4
Requires-Dist: requests
